aws_helpers/__init__.py
aws_helpers/dynamodb_helpers.py
aws_helpers/lambda_helpers.py
aws_helpers/s3_helpers.py
aws_helpers/sns_helpers.py
aws_helpers/sqs_consumer.py
aws_helpers/sqs_helpers.py
aws_helpers/tests/__init__.py
aws_helpers/tests/test_dynamodb_helpers.py
aws_helpers/tests/test_lambda_helpers.py
aws_helpers/tests/test_s3_helpers.py
aws_helpers/tests/test_sns_helpers.py
aws_helpers/tests/test_sqs_consumer.py
aws_helpers/tests/test_sqs_helpers.py
ctodd_python_lib_aws-1.0.0.dist-info/LICENSE.txt
ctodd_python_lib_aws-1.0.0.dist-info/METADATA
ctodd_python_lib_aws-1.0.0.dist-info/RECORD
ctodd_python_lib_aws-1.0.0.dist-info/WHEEL
ctodd_python_lib_aws-1.0.0.dist-info/top_level.txt
