Metadata-Version: 2.1
Name: ctodd-python-lib-aws
Version: 1.0.0
Summary: Python utilities used for interacting with Amazon Web Services
Home-page: https://github.com/ChristopherHaydenTodd/ctodd-python-lib-aws
Author: Christopher H. Todd
Author-email: Christopher.Hayden.Todd@gmail.com
License: MIT
Keywords: python,libraries,aws,S3,SNS,SQS
Platform: UNKNOWN
Classifier: Development Status :: 5 - Production/Stable
Classifier: Intended Audience :: Developers
Classifier: Natural Language :: English
Classifier: Programming Language :: Python
Classifier: Programming Language :: Python :: 3
Classifier: Programming Language :: Python :: 3.6
Classifier: Programming Language :: Python :: 3.7
Classifier: Programming Language :: Python :: 3.8
Requires-Python: >3.6
Requires-Dist: wrapt (>=1.10.8)
Requires-Dist: boto3 (>=1.7.32)
Requires-Dist: botocore (>=1.12.71)
